pytket/__init__.py
pytket/_version.py
pytket/py.typed
pytket/_tket/__init__.py
pytket/_tket/__init__.pyi
pytket/_tket/architecture.cpython-311-aarch64-linux-gnu.so
pytket/_tket/architecture.pyi
pytket/_tket/circuit.cpython-311-aarch64-linux-gnu.so
pytket/_tket/circuit.pyi
pytket/_tket/circuit_library.cpython-311-aarch64-linux-gnu.so
pytket/_tket/circuit_library.pyi
pytket/_tket/libtket.so
pytket/_tket/libtklog.so
pytket/_tket/logging.cpython-311-aarch64-linux-gnu.so
pytket/_tket/logging.pyi
pytket/_tket/mapping.cpython-311-aarch64-linux-gnu.so
pytket/_tket/mapping.pyi
pytket/_tket/partition.cpython-311-aarch64-linux-gnu.so
pytket/_tket/partition.pyi
pytket/_tket/passes.cpython-311-aarch64-linux-gnu.so
pytket/_tket/passes.pyi
pytket/_tket/pauli.cpython-311-aarch64-linux-gnu.so
pytket/_tket/pauli.pyi
pytket/_tket/placement.cpython-311-aarch64-linux-gnu.so
pytket/_tket/placement.pyi
pytket/_tket/predicates.cpython-311-aarch64-linux-gnu.so
pytket/_tket/predicates.pyi
pytket/_tket/tableau.cpython-311-aarch64-linux-gnu.so
pytket/_tket/tableau.pyi
pytket/_tket/tailoring.cpython-311-aarch64-linux-gnu.so
pytket/_tket/tailoring.pyi
pytket/_tket/transform.cpython-311-aarch64-linux-gnu.so
pytket/_tket/transform.pyi
pytket/_tket/unit_id.cpython-311-aarch64-linux-gnu.so
pytket/_tket/unit_id.pyi
pytket/_tket/utils_serialization.cpython-311-aarch64-linux-gnu.so
pytket/_tket/utils_serialization.pyi
pytket/_tket/zx.cpython-311-aarch64-linux-gnu.so
pytket/_tket/zx.pyi
pytket/architecture/__init__.py
pytket/backends/__init__.py
pytket/backends/backend.py
pytket/backends/backend_exceptions.py
pytket/backends/backendinfo.py
pytket/backends/backendresult.py
pytket/backends/resulthandle.py
pytket/backends/status.py
pytket/circuit/__init__.py
pytket/circuit/add_condition.py
pytket/circuit/clexpr.py
pytket/circuit/decompose_classical.py
pytket/circuit/logic_exp.py
pytket/circuit/named_types.py
pytket/circuit/display/__init__.py
pytket-2.12.0.dist-info/METADATA
pytket-2.12.0.dist-info/WHEEL
pytket-2.12.0.dist-info/top_level.txt
pytket-2.12.0.dist-info/RECORD
