Metadata-Version: 2.4
Name: pytket
Version: 2.12.0
Summary: Quantum computing toolkit and interface to the TKET compiler
Author: TKET development team
Author-email: tket-support@quantinuum.com
License: Apache 2
Project-URL: Documentation, https://docs.quantinuum.com/tket/api-docs/
Project-URL: Source, https://github.com/quantinuum/tket
Project-URL: Tracker, https://github.com/quantinuum/tket/issues
Classifier: Environment :: Console
Classifier: Programming Language :: Python :: 3.10
Classifier: Programming Language :: Python :: 3.11
Classifier: Programming Language :: Python :: 3.12
Classifier: Programming Language :: Python :: 3.13
Classifier: Programming Language :: Python :: 3.14
Classifier: License :: OSI Approved :: Apache Software License
Classifier: Operating System :: MacOS :: MacOS X
Classifier: Operating System :: POSIX :: Linux
Classifier: Operating System :: Microsoft :: Windows
Classifier: Intended Audience :: Developers
Classifier: Intended Audience :: Science/Research
Classifier: Topic :: Scientific/Engineering
Requires-Python: >=3.10
Requires-Dist: sympy>=1.12.1
Requires-Dist: numpy>=1.26.4
Requires-Dist: lark>=1.1.9
Requires-Dist: scipy>=1.13.1
Requires-Dist: networkx>=2.8.8
Requires-Dist: graphviz>=0.20.3
Requires-Dist: jinja2>=3.1.4
Requires-Dist: typing-extensions>=4.12.2
Requires-Dist: qwasm>=1.0.1
Provides-Extra: zx
Requires-Dist: numba>=0.62.1; extra == "zx"
Requires-Dist: quimb>=1.8.2; extra == "zx"
Requires-Dist: autoray>=0.6.12; extra == "zx"
Dynamic: author
Dynamic: author-email
Dynamic: classifier
Dynamic: description
Dynamic: description-content-type
Dynamic: license
Dynamic: project-url
Dynamic: provides-extra
Dynamic: requires-dist
Dynamic: requires-python
Dynamic: summary
